yolov4_cv/__init__.py
yolov4_cv/datadefine.py
yolov4_cv/model.py
yolov4_cv-0.0.1.dist-info/METADATA
yolov4_cv-0.0.1.dist-info/WHEEL
yolov4_cv-0.0.1.dist-info/top_level.txt
yolov4_cv-0.0.1.dist-info/RECORD
